{
    "a" : "ա",
    "b" : "բ",
    "g" : "գ",
    "d" : "դ",
    "ye" : "ե",
    "z" : "զ",
    "@" : "ը",
    "zh" : "ժ",
    "i" : "ի",
    "l" : "լ",
    "kh" : "խ",
    "ts" : "ծ",
    "k" : "կ",
    "h" : "հ",
    "dz" : "ձ",
    "gh" : "ղ",
    "tch" : "ճ",
    "m" : "մ",
    "y" : "յ",
    "n" : "ն",
    "sh" : "շ",
    "vo" : "ո",
    "ch" : "չ",
    "p" : "պ",
    "j" : "ջ",
    "s" : "ս",
    "v" : "վ",
    "t" : "տ",
    "r" : "ր",
    "c" : "ց",
    "u" : "ու",
    "ph" : "փ",
    "q": "ք",
    "yev" : "և",
    "o" : "ո",
    "f" : "ֆ",
    "e" : "ե",
    "," : ",",
    "." : ":"
}